<?xml version="1.0" encoding="UTF-8"?>
<team>
	<name>Morocco</name>
	<goalRating>12</goalRating>
	<formation>3-5-2</formation>
	<strategy>Normal</strategy>
	<halfStats>
		<attempts>10</attempts>
		<defensiveAttempts>-6</defensiveAttempts>
		<defensiveShotsOnGoal>-4</defensiveShotsOnGoal>
	</halfStats>
	<halfStats>
		<attempts>7</attempts>
		<defensiveAttempts>-2</defensiveAttempts>
		<defensiveShotsOnGoal>-2</defensiveShotsOnGoal>
	</halfStats>
	<players>
		<player>
			<name>Khairi</name>
			<shotRange>1-55</shotRange>
			<goal>6-10</goal>
			<injury>1-10</injury>
			<multiplier>0</multiplier>
		</player>
		<player>
			<name>Krimau</name>
			<shotRange>56-83</shotRange>
			<goal>6-10</goal>
			<injury>11-16</injury>
			<multiplier>0</multiplier>
		</player>
		<player>
			<name>Timoumi</name>
			<shotRange>84</shotRange>
			<goal>8-10</goal>
			<injury>17-26</injury>
			<multiplier>0</multiplier>
		</player>
		<player>
			<name>Aziz Soulaymani</name>
			<shotRange>85</shotRange>
			<goal>8-10</goal>
			<injury>27-30</injury>
			<multiplier>0</multiplier>
		</player>
		<player>
			<name>Oudani</name>
			<shotRange>86</shotRange>
			<goal>8-10</goal>
			<injury>31-33</injury>
			<multiplier>0</multiplier>
		</player>
		<player>
			<name>Bouderbala</name>
			<shotRange>87</shotRange>
			<goal>9-10</goal>
			<injury>34-39</injury>
			<multiplier>0</multiplier>
		</player>
		<player>
			<name>Merry</name>
			<shotRange>88</shotRange>
			<goal>9-10</goal>
			<injury>40-42</injury>
			<multiplier>0</multiplier>
		</player>
		<player>
			<name>Khalifa</name>
			<shotRange>89</shotRange>
			<goal>9-10</goal>
			<injury>43-57</injury>
			<multiplier>0</multiplier>
		</player>
		<player>
			<name>Lamriss</name>
			<shotRange>90</shotRange>
			<goal>10</goal>
			<injury>58-67</injury>
			<multiplier>0</multiplier>
		</player>
		<player>
			<name>Bouyahyaoui</name>
			<shotRange>91</shotRange>
			<goal>10</goal>
			<injury>68-73</injury>
			<multiplier>0</multiplier>
		</player>
		<player>
			<name>Dolmy</name>
			<shotRange>92</shotRange>
			<goal>10</goal>
			<injury>74-79</injury>
			<multiplier>0</multiplier>
		</player>
		<player>
			<name>El Hadaoui</name>
			<shotRange>93</shotRange>
			<goal>10</goal>
			<injury>80-83</injury>
			<multiplier>0</multiplier>
		</player>
		<player>
			<name>El Biyaz</name>
			<shotRange>94</shotRange>
			<goal>10</goal>
			<injury>84-87</injury>
			<multiplier>0</multiplier>
		</player>
		<player>
			<name>Rhiati</name>
			<shotRange>95</shotRange>
			<goal>10</goal>
			<injury>88</injury>
			<multiplier>0</multiplier>
		</player>
		<player>
			<name>El Haddaoui</name>
			<shotRange>96</shotRange>
			<goal>10</goal>
			<injury>89</injury>
			<multiplier>0</multiplier>
		</player>
		<player>
			<name>Amanallah</name>
			<shotRange>97</shotRange>
			<goal>10</goal>
			<injury>90</injury>
			<multiplier>0</multiplier>
		</player>
		<player>
			<name>Sahil</name>
			<shotRange>98</shotRange>
			<goal>10</goal>
			<injury>91</injury>
			<multiplier>0</multiplier>
		</player>
		<player>
			<name>Jilal</name>
			<shotRange>99</shotRange>
			<goal>10</goal>
			<injury>92</injury>
			<multiplier>0</multiplier>
		</player>
		<player>
			<name>Bidar</name>
			<shotRange>100</shotRange>
			<goal>10</goal>
			<injury>93</injury>
			<multiplier>0</multiplier>
		</player>
		<goalie>
			<name>Zaki</name>
			<rating>-1</rating>
			<injury>94-98</injury>
			<multiplier>2</multiplier>
		</goalie>
		<goalie>
			<name>Hmied</name>
			<rating>0</rating>
			<injury>99-100</injury>
			<multiplier>0</multiplier>
		</goalie>
		<goalie>
			<name>Mouddani</name>
			<rating>+1</rating>
			<injury>x</injury>
			<multiplier>0</multiplier>
		</goalie>
	</players>
</team>
